pycloudshare/__init__.py
pycloudshare/accelerate.py
pycloudshare/classic.py
pycloudshare/infrastructure.py
pycloudshare/utils.py
pycloudshare-1.0.data/scripts/manage-cloudshare.py
pycloudshare-1.0.dist-info/METADATA
pycloudshare-1.0.dist-info/WHEEL
pycloudshare-1.0.dist-info/top_level.txt
pycloudshare-1.0.dist-info/RECORD
